allegro_auth/__init__.py
allegro_auth/client.py
allegro_auth/config.py
allegro_auth/schema.py
allegro_auth/token_manager.py
allegro_auth-2.1.0.dist-info/METADATA
allegro_auth-2.1.0.dist-info/WHEEL
allegro_auth-2.1.0.dist-info/licenses/LICENCE
allegro_auth-2.1.0.dist-info/RECORD
