Metadata-Version: 2.4
Name: allegro_auth
Version: 2.1.0
Summary: This Python package handles authentication with the Allegro API using OAuth2.
Project-URL: Homepage, https://github.com/veritasdol/allegro_auth
Project-URL: Issues, https://github.com/veritasdol/allegro_auth/issues
Author-email: Serhii Dolhopolov <veritas.dol@gmail.com>
License-Expression: MIT
License-File: LICENCE
Classifier: Operating System :: OS Independent
Classifier: Programming Language :: Python :: 3
Requires-Python: >=3.9
Requires-Dist: platformdirs
Requires-Dist: pydantic
Requires-Dist: python-dotenv
Requires-Dist: requests
Provides-Extra: test
Requires-Dist: pytest; extra == 'test'
